crackify/__init__.py
crackify/core.py
crackify/version.py
crackify-0.1.2.dist-info/METADATA
crackify-0.1.2.dist-info/WHEEL
crackify-0.1.2.dist-info/top_level.txt
crackify-0.1.2.dist-info/RECORD
