Metadata-Version: 2.4
Name: crackify
Version: 0.1.2
Summary: Terminal-based Spotify artist autostreamer (headless, requires librespot)
Home-page: https://github.com/yourgithub/crackify
Author: YOUR NAME
Author-email: DriizzyyB <driizzyyboosts@gmail.com>
Project-URL: Homepage, https://github.com/driizzyy
Project-URL: Repository, https://github.com/driizzyy/crackify
Project-URL: Issues, https://github.com/driizzyy/crackify/issues
Keywords: spotify,streaming,librespot,music,headless
Classifier: Programming Language :: Python :: 3
Classifier: License :: OSI Approved :: MIT License
Classifier: Operating System :: OS Independent
Classifier: Intended Audience :: Developers
Classifier: Topic :: Multimedia :: Sound/Audio :: Players
Requires-Python: >=3.7
Requires-Dist: spotipy>=2.23.0
Requires-Dist: python-dotenv>=1.0.0
Dynamic: author
Dynamic: home-page
Dynamic: requires-python
